LICENSE
MANIFEST.in
NOTICE
README.md
setup.cfg
setup.py
versioneer.py
pymc3_hmm/__init__.py
pymc3_hmm/_version.py
pymc3_hmm/distributions.py
pymc3_hmm/step_methods.py
pymc3_hmm/utils.py
pymc3_hmm.egg-info/PKG-INFO
pymc3_hmm.egg-info/SOURCES.txt
pymc3_hmm.egg-info/dependency_links.txt
pymc3_hmm.egg-info/not-zip-safe
pymc3_hmm.egg-info/requires.txt
pymc3_hmm.egg-info/top_level.txt