Metadata-Version: 2.1
Name: pymc3-hmm
Version: 0.2.3
Summary: Hidden Markov Models in PyMC3
Home-page: http://github.com/AmpersandTV/pymc3-hmm
Maintainer: Brandon T. Willard
Maintainer-email: brandonwillard+pymc3_hmm@gmail.com
License: UNKNOWN
Platform: UNKNOWN
Classifier: Development Status :: 4 - Beta
Classifier: Intended Audience :: Science/Research
Classifier: Intended Audience :: Developers
Classifier: License :: OSI Approved :: Apache Software License
Classifier: Operating System :: OS Independent
Classifier: Programming Language :: Python
Classifier: Programming Language :: Python :: 3
Classifier: Programming Language :: Python :: 3.6
Classifier: Programming Language :: Python :: 3.7
Classifier: Programming Language :: Python :: 3.8
Classifier: Programming Language :: Python :: Implementation :: CPython
Classifier: Programming Language :: Python :: Implementation :: PyPy
Requires-Python: >=3.6
